setup.py
mr_bot/__init__.py
mr_bot/geolocator.py
mr_bot/keyboard.py
mr_bot/responder.py
mr_bot/sender.py
mr_bot/settings.py
mr_bot/ui.py
mr_bot.egg-info/PKG-INFO
mr_bot.egg-info/SOURCES.txt
mr_bot.egg-info/dependency_links.txt
mr_bot.egg-info/requires.txt
mr_bot.egg-info/top_level.txt