Metadata-Version: 1.1
Name: mr-bot
Version: 1.1.3
Summary: Small package for assist telegram bot development
Home-page: https://github.com/r00tkid/mr_bot.git
Author: Root Kid
Author-email: shaman@born2fish.ru
License: UNKNOWN
Download-URL: https://github.com/r00tkid/mr_bot/tarball/1.1.3
Keywords: support,telegram,bot,keyboard
Platform: UNKNOWN
